<realmManager>
   <realmMap>
      <entry>
         <string>ThisIsAQRCode</string>
         <realm Name="ThisIsAQRCode" QRUnitSize="3.0">
            <objectMap class="java.util.HashMap">
               <entry>
                  <string>TestObj2</string>
                  <ARObject Name="TestObj2" ModelName="cube.obj">
                     <Position X="-40.0" Y="0.0" Z="0.0"/>
                     <Rotation X="-1.1" Y="2.1" Z="3.1"/>
                     <Scale X="15.0" Y="20.0" Z="10.0"/>
                     <BoundingSphereRadius>18.0</BoundingSphereRadius>
                  </ARObject>
               </entry>
               <entry>
                  <string>TestObj1</string>
                  <ARObject Name="TestObj1" ModelName="cube.obj">
                     <Position X="19.637335" Y="-4.581993" Z="0.16491699"/>
                     <Rotation X="0.0" Y="0.0" Z="0.0"/>
                     <Scale X="15.0" Y="10.0" Z="15.0"/>
                     <BoundingSphereRadius>15.0</BoundingSphereRadius>
                  </ARObject>
               </entry>
            </objectMap>
         </realm>
      </entry>
      <entry>
         <string>TestRealm_2</string>
         <realm Name="TestRealm_2" QRUnitSize="2.0">
            <objectMap class="java.util.HashMap">
               <entry>
                  <string>TestObj3</string>
                  <ARObject Name="TestObj3" ModelName="cube.obj">
                     <Position X="0.0" Y="-20.0" Z="0.0"/>
                     <Rotation X="0.0" Y="0.0" Z="0.0"/>
                     <Scale X="15.0" Y="15.0" Z="15.0"/>
                     <BoundingSphereRadius>20.0</BoundingSphereRadius>
                  </ARObject>
               </entry>
               <entry>
                  <string>TestObj2</string>
                  <ARObject Name="TestObj2" ModelName="cube.obj">
                     <Position X="-20.0" Y="20.0" Z="0.0"/>
                     <Rotation X="0.0" Y="0.0" Z="0.0"/>
                     <Scale X="15.0" Y="15.0" Z="15.0"/>
                     <BoundingSphereRadius>20.0</BoundingSphereRadius>
                  </ARObject>
               </entry>
               <entry>
                  <string>TestObj1</string>
                  <ARObject Name="TestObj1" ModelName="cube.obj">
                     <Position X="20.0" Y="20.0" Z="0.0"/>
                     <Rotation X="0.0" Y="0.0" Z="0.0"/>
                     <Scale X="15.0" Y="15.0" Z="15.0"/>
                     <BoundingSphereRadius>20.0</BoundingSphereRadius>
                  </ARObject>
               </entry>
            </objectMap>
         </realm>
      </entry>
      <entry>
         <string>ThoughtWorks Interactive Technologies</string>
         <realm Name="ThoughtWorks Interactive Technologies" QRUnitSize="10.0">
            <objectMap class="java.util.HashMap">
               <entry>
                  <string>user_obj_2</string>
                  <ARObject Name="user_obj_2" ModelName="Cube" Action="Create">
                     <Position X="0.0" Y="0.0" Z="0.0"/>
                     <Rotation X="0.0" Y="0.0" Z="0.0"/>
                     <Scale X="0.0" Y="0.0" Z="0.0"/>
                     <BoundingSphereRadius>0.0</BoundingSphereRadius>
                  </ARObject>
               </entry>
               <entry>
                  <string>user_obj_1</string>
                  <ARObject Name="user_obj_1" ModelName="Cube" Action="Create">
                     <Position X="-21.479557" Y="34.420956" Z="4.924469"/>
                     <Rotation X="0.0" Y="0.0" Z="0.0"/>
                     <Scale X="0.0" Y="0.0" Z="0.0"/>
                     <BoundingSphereRadius>0.0</BoundingSphereRadius>
                  </ARObject>
               </entry>
            </objectMap>
         </realm>
      </entry>
      <entry>
         <string>UnknownRealm</string>
         <realm Name="UnknownRealm" QRUnitSize="10.0">
            <objectMap class="java.util.HashMap">
               <entry>
                  <string>user_obj_1</string>
                  <ARObject Name="user_obj_1" ModelName="Cube" Action="Create">
                     <Position X="15.464287" Y="-28.263788" Z="-18.6305"/>
                     <Rotation X="0.0" Y="0.0" Z="0.0"/>
                     <Scale X="1.0" Y="1.0" Z="1.0"/>
                     <BoundingSphereRadius>0.0</BoundingSphereRadius>
                  </ARObject>
               </entry>
            </objectMap>
         </realm>
      </entry>
   </realmMap>
   <credentialMap>
      <entry>
         <string>TestUser2</string>
         <string>G6PRbpiBlZ+MmpdihU9yxuYyHN1ENYoQpOk5AzEX6rk=</string>
      </entry>
      <entry>
         <string>AdamSkubel</string>
         <string>dlSbgn7EbnBf0DgxgT+lIXIzjw38vXEe1EuBqW2sUcY=</string>
      </entry>
      <entry>
         <string>TestUser</string>
         <string>5sPaWyBmNNfz81htdH/9s2tcZ1dXs4DGpf5cVwxxQ0k=</string>
      </entry>
   </credentialMap>
</realmManager>